wordpress_auth/decorators.py
wordpress_auth/utils.py
wordpress_auth/__init__.py
wordpress_auth/middleware.py
wordpress_auth/views.py
wordpress_auth/models.py
django_wordpress_auth-0.1.31.dist-info/top_level.txt
django_wordpress_auth-0.1.31.dist-info/metadata.json
django_wordpress_auth-0.1.31.dist-info/RECORD
django_wordpress_auth-0.1.31.dist-info/METADATA
django_wordpress_auth-0.1.31.dist-info/DESCRIPTION.rst
django_wordpress_auth-0.1.31.dist-info/WHEEL
